{
  "version": 1,
  "date": "2026-07-17",
  "timezone": "Asia/Dhaka",
  "createdAt": "2026-07-16T21:30:37.150Z",
  "snapshotCount": 4,
  "plannerSnapshotIncluded": true,
  "selectedSlots": [
    {
      "id": "slot-02",
      "cron": "43 4 * * *",
      "utcTime": "04:43"
    },
    {
      "id": "slot-03",
      "cron": "11 8 * * *",
      "utcTime": "08:11"
    },
    {
      "id": "slot-07",
      "cron": "23 21 * * *",
      "utcTime": "21:23"
    }
  ],
  "completedSlots": [
    {
      "slotId": "slot-07",
      "completedAt": "2026-07-16T22:27:10.774Z",
      "snapshotPath": "data/snapshots/2026/07/16/2026-07-16T22-27-10-514Z-8645.json"
    },
    {
      "slotId": "slot-02",
      "completedAt": "2026-07-17T07:03:52.980Z",
      "snapshotPath": "data/snapshots/2026/07/17/2026-07-17T07-03-52-725Z-7397.json"
    }
  ]
}
